samping/__init__.py
samping/backoff.py
samping/channel.py
samping/exceptions.py
samping/messages.py
samping/routes.py
samping/serialization.py
samping/types.py
samping/worker.py
samping/adapters/__init__.py
samping/adapters/aws_lambda.py
samping/app/__init__.py
samping/app/app.py
samping/app/conf.py
samping/app/tracer.py
samping/driver/__init__.py
samping/driver/sqs.py
samping/protocol/__init__.py
samping/protocol/lifespan.py
samping/protocol/queue.py
samping/tasks/__init__.py
samping/tasks/request.py
samping/tasks/tasks.py
samping/utils/__init__.py
samping/utils/btree.py
samping/utils/compat.py
samping/utils/encoding.py
samping/utils/format.py
samping/utils/iterators.py
samping/utils/json.py
samping/utils/sqs.py
samping/utils/text.py
samping/utils/time.py
samping/utils/timer.py
samping-0.3.1.dist-info/METADATA
samping-0.3.1.dist-info/WHEEL
samping-0.3.1.dist-info/RECORD
