Metadata-Version: 2.3
Name: samping
Version: 0.3.1
Summary: simple task queue library and background task processing
Author-email: syaiful6 <syai.bahri6@gmail.com>
Requires-Python: >=3.10
Requires-Dist: croniter>=2.0.3
Requires-Dist: msgpack>=1.0.5
Requires-Dist: pytz>=2022.7.1
